{"source":"AngolaEmprego","source_url":"https://www.angolaemprego.com/vagas/grande-oportunidade-vaga-na-nestle-angola","title":"Grande Oportunidade: Vaga na Nestlé Angola","company":"Nestlé Angola","location":"Angola","category":"Design","description":"Oportunidade de Emprego: Analista de Soluções para Clientes na Nestlé Angola\n<p>\nA <strong>Nestlé Angola</strong>, líder global no sector de alimentos e bebidas, está a recrutar um <strong>Analista de Soluções para Clientes</strong> para reforçar a sua equipa em <strong>Luanda</strong>.\n</p>\n<p>\nEsta é uma excelente oportunidade para profissionais que desejam crescer numa multinacional com impacto global.\n</p>\n<p>\n📍 Local: Luanda<br>\n<strong>Tipo:</strong> Temporário\n</p>\n<h4>🎯 Missão da função</h4>\n<p>\nGerir e optimizar o processo <strong>Order-to-Cash (do pedido ao recebimento)</strong>, garantindo eficiência operacional, satisfação do cliente e melhoria contínua dos processos.\n</p>\n<h4>💼 Principais responsabilidades</h4>\n<ul>\n<li>Coordenar iniciativas de desenvolvimento e gestão de clientes</li>\n<li>Actuar como ponto de contacto entre clientes e cadeia de abastecimento</li>\n<li>Garantir planeamento eficiente da procura</li>\n<li>Monitorar encomendas e processos de faturação</li>\n<li>Analisar métricas (reclamações, devoluções, falhas)</li>\n<li>Identificar tendências e propor melhorias</li>\n<li>Desenvolver e apoiar equipas de atendimento ao cliente</li>\n</ul>\n<h4>🎓 Requisitos</h4>\n<ul>\n<li>Licenciatura em:\n<ul>\n<li>Administração</li>\n<li>Economia</li>\n<li>Logística</li>\n<li>Áreas afins</li>\n</ul>\n</li>\n<li>Experiência de <strong>1 a 2 anos</strong> em:\n<ul>\n<li>Atendimento ao cliente</li>\n<li>Logística ou planeamento de demanda</li>\n<li>Vendas ou gestão de contas</li>\n<li>Gestão de projetos.</li>\n</ul>\n</li>\n</ul>\n<h4>📨 Candidaturas</h4>\n<p>\n🔗 Candidate-se através do link oficial:<br>\n👉 https://jobdetails.nestle.com/job/Luanda-Customer-Solution-Analyst/1387566633/\n</p>\n            Partilhar:\n            <i></i>\n            <i></i>\n            <i></i>\n                Categorias\n                                      Admininistração e Gestão\n                                      Administrativo e Secretariado\n                                      Agropecuária e Pesca\n                                      Alimentação e Nutrição\n                                      Ambiente\n                                      Arquitectura\n                                      Atendimento ao Cliente\n                                      Auditoria\n                                      Aviação\n                                      Banca e Seguros\n                                      Beleza\n                                      Bolsas de Estudos\n                                      Comercial\n                                      Comunicação Social\n                                      Concurso Público\n                                      Construção Civil\n                                      Consultoria\n                                      Contabilidade\n                                      Costura\n                                      Cozinha\n                                      Culinária\n                                      Design\n                                      Desportos\n                                      Economia\n                                      Educação e Ensino\n                                      Electricidade\n                                      Engenharia\n                                      Estágio\n                                      Estética\n                                      Farmácia\n                                      Finanças\n                                      Fotografia e Vídeo\n                                      Freelancer\n                                      Hotelaria e Turismo\n                                      Informática e Tecnologias\n                                      Jurídico\n                                      Línguas\n                                      Logística\n                                      Marketing Digital\n                                      Marketing e Publicidade\n                                      Mecánica\n                                      Medicina\n                                      Petrolífero\n                                      Recursos Humanos\n                                      Transportes\n                Vagas Recentes\n                    <i></i>\n                      SLB Angola: Oportunidades em 15 Áreas – Engenharia, Geologia, TI, RH, Manutenção e Estágios\n                      SLB (Schlumberger)\n                    <i></i>\n                      Vaga para Vendedor(a) de Rota | Canal Tradicional - Água Weya\n                      Agrobal Sociedade Comercial e Industrial Agricola, Lda\n                    <i></i>\n                      Vaga para Enfermeiro(a)\n                      Grupo Omatapalo\n                    <i></i>\n                      Vaga para Estágio 2026 — Contabilidade e Fiscalidade\n                      POWERSTORE — Comércio Geral, Lda.\n                    <i></i>\n                      Vaga para Vendedor de Motociclo (2 Rodas)\n                      Brand&#039;s UP (para cliente em Luanda)\n                    <i></i>\n                      Vaga para Especialista em Sistemas de Proteção e Controlo de Subestações\n                      APROT Engenharia\n                    <i></i>\n                      Vaga para Técnico(a) de Recursos Humanos\n                      Empresa em Angola\n                    <i></i>\n                      Vaga para Técnico de IT\n                      LESSO Angola","excerpt":"Oportunidade de Emprego: Analista de Soluções para Clientes na Nestlé Angola A Nestlé Angola , líder global no sector de alimentos e bebidas, está a recrutar um Analista de Soluções para Clientes para reforçar a sua equipa em Luanda . Esta é uma excelente oportunidade para profissionais que desejam ","apply_url":"https://jobdetails.nestle.com/job/Luanda-Customer-Solution-Analyst/1387566633/","salary":"","posted_at":"2026-04-30T07:15:15.000Z","id":"grande-oportunidade-vaga-na-nestle-angola","first_seen_at":"2026-07-18T16:39:17.270Z","score":15,"logo_url":"https://logo.pubrio.com/nestle.com","description_enriched":"Oportunidade de Emprego: Analista de Soluções para Clientes na Nestlé Angola\n<p>\nA <strong>Nestlé Angola</strong>, líder global no sector de alimentos e bebidas, está a recrutar um <strong>Analista de Soluções para Clientes</strong> para reforçar a sua equipa em <strong>Luanda</strong>.\n</p>\n<p>\nEsta é uma excelente oportunidade para profissionais que desejam crescer numa multinacional com impacto global.\n</p>\n<p>\n📍 Local: Luanda<br>\n<strong>Tipo:</strong> Temporário\n</p>\n<h4>🎯 Missão da função</h4>\n<p>\nGerir e optimizar o processo <strong>Order-to-Cash (do pedido ao recebimento)</strong>, garantindo eficiência operacional, satisfação do cliente e melhoria contínua dos processos.\n</p>\n<h4>💼 Principais responsabilidades</h4>\n<ul>\n<li>Coordenar iniciativas de desenvolvimento e gestão de clientes</li>\n<li>Actuar como ponto de contacto entre clientes e cadeia de abastecimento</li>\n<li>Garantir planeamento eficiente da procura</li>\n<li>Monitorar encomendas e processos de faturação</li>\n<li>Analisar métricas (reclamações, devoluções, falhas)</li>\n<li>Identificar tendências e propor melhorias</li>\n<li>Desenvolver e apoiar equipas de atendimento ao cliente</li>\n</ul>\n<h4>🎓 Requisitos</h4>\n<ul>\n<li>Licenciatura em:\n<ul>\n<li>Administração</li>\n<li>Economia</li>\n<li>Logística</li>\n<li>Áreas afins</li>\n</ul>\n</li>\n<li>Experiência de <strong>1 a 2 anos</strong> em:\n<ul>\n<li>Atendimento ao cliente</li>\n<li>Logística ou planeamento de demanda</li>\n<li>Vendas ou gestão de contas</li>\n<li>Gestão de projetos.</li>\n</ul>\n</li>\n</ul>\n<h4>📨 Candidaturas</h4>\n<p>\n🔗 Candidate-se através do link oficial:<br>\n👉 https://jobdetails.nestle.com/job/Luanda-Customer-Solution-Analyst/1387566633/\n</p>\n            Partilhar:\n            <i></i>\n            <i></i>\n            <i></i>\n                Categorias\n                                      Admininistração e Gestão\n                                      Administrativo e Secretariado\n                                      Agropecuária e Pesca\n                                      Alimentação e Nutrição\n                                      Ambiente\n                                      Arquitectura\n                                      Atendimento ao Cliente\n                                      Auditoria\n                                      Aviação\n                                      Banca e Seguros\n                                      Beleza\n                                      Bolsas de Estudos\n                                      Comercial\n                                      Comunicação Social\n                                      Concurso Público\n                                      Construção Civil\n                                      Consultoria\n                                      Contabilidade\n                                      Costura\n                                      Cozinha\n                                      Culinária\n                                      Design\n                                      Desportos\n                                      Economia\n                                      Educação e Ensino\n                                      Electricidade\n                                      Engenharia\n                                      Estágio\n                                      Estética\n                                      Farmácia\n                                      Finanças\n                                      Fotografia e Vídeo\n                                      Freelancer\n                                      Hotelaria e Turismo\n                                      Informática e Tecnologias\n                                      Jurídico\n                                      Línguas\n                                      Logística\n                                      Marketing Digital\n                                      Marketing e Publicidade\n                                      Mecánica\n                                      Medicina\n                                      Petrolífero\n                                      Recursos Humanos\n                                      Transportes\n                Vagas Recentes\n                    <i></i>\n                      Oportunidade para Técnico de Trade Finance\n                      Standard Bank Angola\n                    <i></i>\n                      Grande Oportunidade: Recrutamento de Empregado(a) Doméstico(a) Temporário(a) na Embaixada do Japão em Angola\n                      Embaixada do Japão na República de Angola\n                    <i></i>\n                      Vaga: Chefe de Campo (Camp Boss) em Angola - NEWREST Restauração\n                      NEWREST Restauração, Lda\n                    <i></i>\n                      Vaga para Gestor de QHSE\n                      ES&amp;S Group\n                    <i></i>\n                      Grande Oportunidade para Senior Accountant\n                      St. George\n                    <i></i>\n                      Oportunidade Urgente: Comercial para Frutas &amp; Legumes\n                      Agrogenea Distribuição\n                    <i></i>\n                      Vaga para Chefe de Secção de Brand &amp; Communications em Benguela\n                      Africell Angola\n                    <i></i>\n                      Oportunidade para Coordenador de Oficina Mecânica\n                      Saipem","tipo_contrato":"","modalidade":"","requisitos":"","beneficios":""}