{"source":"AngolaEmprego","source_url":"https://www.angolaemprego.com/vagas/vaga-para-inquiridor-03-posicoes","title":"Vaga para Inquiridor (03 Posições)","company":"World Vision International - Angola","location":"Benguela e Luanda","category":"Saúde","description":"Oportunidade de Emprego: Inquiridores para Projeto da ADPP Angola\n<p>A ADPP Angola, Ajuda de Desenvolvimento de Povo para Povo, é uma ONG de direito Angolano, que actua desde 1986 nas seguintes áreas de desenvolvimento: Educação, Saúde, Desenvolvimento Rural, Agricultura, Ambiente.<br>\nNo âmbito de desenvolvimento do Projecto Ready Plus Benguela Luanda, a ADPP Angola pretende recrutar:</p>\n<h2>1. Objetivo</h2>\n<ul>\n<li>Contratar 3 inquiridores do sexo feminino qualificados para realizar a recolha de dados em pesquisas de campo nas províncias de Luanda e Benguela, com foco em métodos quantitativos e qualitativos, utilizando ferramentas digitais como ODK ou KoboToolbox, e com experiência no trabalho com grupos vulneráveis.</li>\n<li>Destes, duas (2) para a província de Benguela e uma (1) para Luanda</li>\n</ul>\n<h2>2. Descrição das Funções</h2>\n<p><strong>Os inquiridores serão responsáveis por:</strong></p>\n<ul>\n<li>Realizar a recolha de dados em campo utilizando plataformas digitais (ODK ou KoboToolbox).</li>\n<li>Conduzir entrevistas, inquéritos e grupos focais, aplicando metodologias quantitativas e qualitativas.</li>\n<li>Garantir a interação ética e sensível com grupos vulneráveis, respeitando as diretrizes de protecção e confidencialidade.</li>\n<li>Registar e reportar dados de forma precisa e tempestiva.</li>\n<li>Colaborar com a equipa de supervisão para assegurar a qualidade dos dados recolhidos.</li>\n<li>Participar em formações prévias à recolha de dados.</li>\n</ul>\n<h2>3. Requisitos</h2>\n<p>Os candidatos devem cumprir os seguintes critérios:</p>\n<h3>Experiência profissional:</h3>\n<ul>\n<li>Experiência comprovada (mínimo de 2 anos) na recolha de dados utilizando ODK ou KoboToolbox.</li>\n<li>Experiência em condução de pesquisas de campo quantitativas e qualitativas.</li>\n<li>Experiência prévia no trabalho com grupos vulneráveis (ex.: crianças, mulheres, pessoas com deficiência, comunidades marginalizadas).</li>\n</ul>\n<h4>Residência:</h4>\n<ul>\n<li>Residir na província de Luanda.</li>\n</ul>\n<h3>Habilidades técnicas:</h3>\n<ul>\n<li>Familiaridade com dispositivos móveis para recolha de dados digitais.</li>\n<li>Capacidade de interpretar e seguir guiões de inquérito e manuais de pesquisa.</li>\n</ul>\n<h3>Competências pessoais:</h3>\n<ul>\n<li>Boa comunicação verbal e escrita em português.</li>\n<li>Sensibilidade cultural e ética no trato com comunidades vulneráveis.</li>\n<li>Capacidade de trabalhar em equipa e sob pressão.</li>\n</ul>\n<h3>Formação:</h3>\n<ul>\n<li>Nível médio ou superior em ciências sociais, estatística, ou área relacionada (preferencial, mas não obrigatório).</li>\n</ul>\n<h3>Disponibilidade:</h3>\n<ul>\n<li>Disponibilidade para viagens dentro das províncias, se necessário, e para trabalhar em horários flexíveis.</li>\n</ul>\n<h2>4. Critérios de Seleção</h2>\n<ul>\n<li>Avaliação do currículo com base na experiência relevante.</li>\n<li>Entrevista para avaliar competências técnicas e interpessoais.</li>\n<li>Teste prático (se aplicável) para verificar habilidades com ODK/KoboToolbox.</li>\n<li>Verificação de referências profissionais.</li>\n</ul>\n<h2>5. Condições de Trabalho</h2>\n<ul>\n<li>Duração do contrato: Contrato temporário, conforme a duração do projeto (a especificar).</li>\n<li>Remuneração: A definir com base no orçamento do projeto e experiência do candidato.</li>\n<li>Supervisão: Os inquiridores reportarão a um coordenador de campo.</li>\n<li>Equipamento: Dispositivos para recolha de dados serão fornecidos pela organização.</li>\n</ul>\n<h2>6. Submissão de Candidaturas</h2>\n<p>Se és qualificado e disponível, envie a sua candidatura até 19 a 05 de Fevereiro de 2026, para o correio electrónico eliandro.bartolomeu@adpp-angola.org , Assunto do e-mail: “<strong>Candidatura Inquiridores – [Luanda</strong>“.</p>\n<h4>Os candidatos devem enviar:</h4>\n<ul>\n<li>Curriculum Vitae atualizado, destacando experiência relevante.</li>\n<li>Carta de motivação (máximo de 1 página).</li>\n<li>Comprovativo de residência em Luanda ou Benguela (ex.: cópia de bilhete de identidade ou declaração).</li>\n<li>Referências profissionais (opcional, mas preferencial).</li>\n</ul>\n<h2>7. Observações</h2>\n<ul>\n<li>Apenas os candidatos selecionados serão contactados.</li>\n<li>A organização reserva-se o direito de não preencher as vagas caso não sejam encontrados candidatos adequados.</li>\n<li>A contratação está sujeita à disponibilidade de financiamento do projeto</li>\n</ul>\n            Partilhar:\n            <i></i>\n            <i></i>\n            <i></i>\n                Categorias\n                                      Admininistração e Gestão\n                                      Administrativo e Secretariado\n                                      Agropecuária e Pesca\n                                      Alimentação e Nutrição\n                                      Ambiente\n                                      Arquitectura\n                                      Atendimento ao Cliente\n                                      Auditoria\n                                      Aviação\n                                      Banca e Seguros\n                                      Beleza\n                                      Bolsas de Estudos\n                                      Comercial\n                                      Comunicação Social\n                                      Concurso Público\n                                      Construção Civil\n                                      Consultoria\n                                      Contabilidade\n                                      Costura\n                                      Cozinha\n                                      Culinária\n                                      Design\n                                      Desportos\n                                      Economia\n                                      Educação e Ensino\n                                      Electricidade\n                                      Engenharia\n                                      Estágio\n                                      Estética\n                                      Farmácia\n                                      Finanças\n                                      Fotografia e Vídeo\n                                      Freelancer\n                                      Hotelaria e Turismo\n                                      Informática e Tecnologias\n                                      Jurídico\n                                      Línguas\n                                      Logística\n                                      Marketing Digital\n                                      Marketing e Publicidade\n                                      Mecánica\n                                      Medicina\n                                      Petrolífero\n                                      Recursos Humanos\n                                      Transportes\n                Vagas Recentes\n                    <i></i>\n                      Vaga para Comercial — Frutas &amp; Legumes\n                      Agrogenea Distribuição\n                    <i></i>\n                      Vaga para Chefe de Secção de Brand &amp; Communications (Benguela)\n                      Africell Angola\n                    <i></i>\n                      Vaga para Coordenador de Oficina Mecânica\n                      Saipem\n                    <i></i>\n                      Vaga para Técnico de Trade Finance\n                      Standard Bank Angola\n                    <i></i>\n                      Vaga para Senior Accountant (Contabilista Sénior)\n                      St. George\n                    <i></i>\n                      Vaga para QHSE Manager (Gestor de Qualidade, Saúde, Segurança e Ambiente)\n                      ES&amp;S Group (Exceptional Service &amp; Supply)\n                    <i></i>\n                      Vaga para Recepcionista\n                      CNCEC International (Sucursal Angola)\n                    <i></i>\n                      Vaga para Assistente Comercial\n                      Access Bank Angola","excerpt":"Oportunidade de Emprego: Inquiridores para Projeto da ADPP Angola A ADPP Angola, Ajuda de Desenvolvimento de Povo para Povo, é uma ONG de direito Angolano, que actua desde 1986 nas seguintes áreas de desenvolvimento: Educação, Saúde, Desenvolvimento Rural, Agricultura, Ambiente. No âmbito de desenvo","apply_url":"mailto:eliandro.bartolomeu@adpp-angola.org","salary":"","score":25,"posted_at":"2026-01-27T09:40:15.000Z","id":"vaga-para-inquiridor-03-posicoes","description_enriched":"Oportunidade de Emprego: Inquiridores para Projeto da ADPP Angola\n<p>A ADPP Angola, Ajuda de Desenvolvimento de Povo para Povo, é uma ONG de direito Angolano, que actua desde 1986 nas seguintes áreas de desenvolvimento: Educação, Saúde, Desenvolvimento Rural, Agricultura, Ambiente.<br>\nNo âmbito de desenvolvimento do Projecto Ready Plus Benguela Luanda, a ADPP Angola pretende recrutar:</p>\n<h2>1. Objetivo</h2>\n<ul>\n<li>Contratar 3 inquiridores do sexo feminino qualificados para realizar a recolha de dados em pesquisas de campo nas províncias de Luanda e Benguela, com foco em métodos quantitativos e qualitativos, utilizando ferramentas digitais como ODK ou KoboToolbox, e com experiência no trabalho com grupos vulneráveis.</li>\n<li>Destes, duas (2) para a província de Benguela e uma (1) para Luanda</li>\n</ul>\n<h2>2. Descrição das Funções</h2>\n<p><strong>Os inquiridores serão responsáveis por:</strong></p>\n<ul>\n<li>Realizar a recolha de dados em campo utilizando plataformas digitais (ODK ou KoboToolbox).</li>\n<li>Conduzir entrevistas, inquéritos e grupos focais, aplicando metodologias quantitativas e qualitativas.</li>\n<li>Garantir a interação ética e sensível com grupos vulneráveis, respeitando as diretrizes de protecção e confidencialidade.</li>\n<li>Registar e reportar dados de forma precisa e tempestiva.</li>\n<li>Colaborar com a equipa de supervisão para assegurar a qualidade dos dados recolhidos.</li>\n<li>Participar em formações prévias à recolha de dados.</li>\n</ul>\n<h2>3. Requisitos</h2>\n<p>Os candidatos devem cumprir os seguintes critérios:</p>\n<h3>Experiência profissional:</h3>\n<ul>\n<li>Experiência comprovada (mínimo de 2 anos) na recolha de dados utilizando ODK ou KoboToolbox.</li>\n<li>Experiência em condução de pesquisas de campo quantitativas e qualitativas.</li>\n<li>Experiência prévia no trabalho com grupos vulneráveis (ex.: crianças, mulheres, pessoas com deficiência, comunidades marginalizadas).</li>\n</ul>\n<h4>Residência:</h4>\n<ul>\n<li>Residir na província de Luanda.</li>\n</ul>\n<h3>Habilidades técnicas:</h3>\n<ul>\n<li>Familiaridade com dispositivos móveis para recolha de dados digitais.</li>\n<li>Capacidade de interpretar e seguir guiões de inquérito e manuais de pesquisa.</li>\n</ul>\n<h3>Competências pessoais:</h3>\n<ul>\n<li>Boa comunicação verbal e escrita em português.</li>\n<li>Sensibilidade cultural e ética no trato com comunidades vulneráveis.</li>\n<li>Capacidade de trabalhar em equipa e sob pressão.</li>\n</ul>\n<h3>Formação:</h3>\n<ul>\n<li>Nível médio ou superior em ciências sociais, estatística, ou área relacionada (preferencial, mas não obrigatório).</li>\n</ul>\n<h3>Disponibilidade:</h3>\n<ul>\n<li>Disponibilidade para viagens dentro das províncias, se necessário, e para trabalhar em horários flexíveis.</li>\n</ul>\n<h2>4. Critérios de Seleção</h2>\n<ul>\n<li>Avaliação do currículo com base na experiência relevante.</li>\n<li>Entrevista para avaliar competências técnicas e interpessoais.</li>\n<li>Teste prático (se aplicável) para verificar habilidades com ODK/KoboToolbox.</li>\n<li>Verificação de referências profissionais.</li>\n</ul>\n<h2>5. Condições de Trabalho</h2>\n<ul>\n<li>Duração do contrato: Contrato temporário, conforme a duração do projeto (a especificar).</li>\n<li>Remuneração: A definir com base no orçamento do projeto e experiência do candidato.</li>\n<li>Supervisão: Os inquiridores reportarão a um coordenador de campo.</li>\n<li>Equipamento: Dispositivos para recolha de dados serão fornecidos pela organização.</li>\n</ul>\n<h2>6. Submissão de Candidaturas</h2>\n<p>Se és qualificado e disponível, envie a sua candidatura até 19 a 05 de Fevereiro de 2026, para o correio electrónico eliandro.bartolomeu@adpp-angola.org , Assunto do e-mail: “<strong>Candidatura Inquiridores – [Luanda</strong>“.</p>\n<h4>Os candidatos devem enviar:</h4>\n<ul>\n<li>Curriculum Vitae atualizado, destacando experiência relevante.</li>\n<li>Carta de motivação (máximo de 1 página).</li>\n<li>Comprovativo de residência em Luanda ou Benguela (ex.: cópia de bilhete de identidade ou declaração).</li>\n<li>Referências profissionais (opcional, mas preferencial).</li>\n</ul>\n<h2>7. Observações</h2>\n<ul>\n<li>Apenas os candidatos selecionados serão contactados.</li>\n<li>A organização reserva-se o direito de não preencher as vagas caso não sejam encontrados candidatos adequados.</li>\n<li>A contratação está sujeita à disponibilidade de financiamento do projeto</li>\n</ul>\n            Partilhar:\n            <i></i>\n            <i></i>\n            <i></i>\n                Categorias\n                                      Admininistração e Gestão\n                                      Administrativo e Secretariado\n                                      Agropecuária e Pesca\n                                      Alimentação e Nutrição\n                                      Ambiente\n                                      Arquitectura\n                                      Atendimento ao Cliente\n                                      Auditoria\n                                      Aviação\n                                      Banca e Seguros\n                                      Beleza\n                                      Bolsas de Estudos\n                                      Comercial\n                                      Comunicação Social\n                                      Concurso Público\n                                      Construção Civil\n                                      Consultoria\n                                      Contabilidade\n                                      Costura\n                                      Cozinha\n                                      Culinária\n                                      Design\n                                      Desportos\n                                      Economia\n                                      Educação e Ensino\n                                      Electricidade\n                                      Engenharia\n                                      Estágio\n                                      Estética\n                                      Farmácia\n                                      Finanças\n                                      Fotografia e Vídeo\n                                      Freelancer\n                                      Hotelaria e Turismo\n                                      Informática e Tecnologias\n                                      Jurídico\n                                      Línguas\n                                      Logística\n                                      Marketing Digital\n                                      Marketing e Publicidade\n                                      Mecánica\n                                      Medicina\n                                      Petrolífero\n                                      Recursos Humanos\n                                      Transportes\n                Vagas Recentes\n                    <i></i>\n                      Oportunidade para Técnico de Trade Finance\n                      Standard Bank Angola\n                    <i></i>\n                      Grande Oportunidade: Recrutamento de Empregado(a) Doméstico(a) Temporário(a) na Embaixada do Japão em Angola\n                      Embaixada do Japão na República de Angola\n                    <i></i>\n                      Vaga: Chefe de Campo (Camp Boss) em Angola - NEWREST Restauração\n                      NEWREST Restauração, Lda\n                    <i></i>\n                      Vaga para Gestor de QHSE\n                      ES&amp;S Group\n                    <i></i>\n                      Grande Oportunidade para Senior Accountant\n                      St. George\n                    <i></i>\n                      Oportunidade Urgente: Comercial para Frutas &amp; Legumes\n                      Agrogenea Distribuição\n                    <i></i>\n                      Vaga para Chefe de Secção de Brand &amp; Communications em Benguela\n                      Africell Angola\n                    <i></i>\n                      Oportunidade para Coordenador de Oficina Mecânica\n                      Saipem","tipo_contrato":"","modalidade":"","requisitos":"","beneficios":"","first_seen_at":"2026-07-23T10:03:08.006Z"}