{"source":"AngolaEmprego","source_url":"https://www.angolaemprego.com/vagas/vaga-para-tecnicoa-de-investigacao-de-auditoria","title":"Vaga para Técnico(a) de Investigação de Auditoria","company":"Ver empresa: Access Bank Angola Access Bank Angola","location":"Luanda","category":"Contabilidade","description":"<h3><strong>Sobre a vaga</strong></h3>\n<p>Os(as) candidatos(as) interessados(as) deverão submeter a sua candidatura até 08 de Maio de 2026, mencionando a referência <strong>Invest_2026</strong>, para o endereço de correio electrónico.</p>\n<p>Estamos a recrutar</p>\n<p><strong>Técnico(a) de Investigação de Auditoria</strong></p>\n<p><strong>Formação</strong><br>\n/ Licenciatura em Economia, Auditoria, Gestão de Empresas, Finanças, Contabilidade ou área<br>\nsimilar.</p>\n<p><strong>Experiência</strong><br>\n/ Experiência mínima de 2 anos em funções relacionadas com auditoria (interna e externa), compliance e controlo interno, preferencialmente no setor bancário.</p>\n<p><strong>Principais Responsabilidades</strong><br>\n/ Efectuar auditorias aos departamentos, cumprindo rigorosamente o calendário definido;<br>\n/ Recolher e analisar a informação disponibilizada;<br>\n/ Elaborar relatórios e propor recomendações com vista à melhoria da eficácia dos serviços;<br>\n/ Produzir relatórios sobre o controlo interno dos processos existentes nos diferentes departamentos;<br>\n/ Acompanhar e prestar apoio ao auditor externo, sempre que necessário;<br>\n/ Reportar regularmente informações relevantes que possam ter impacto nas actividades da instituição;<br>\n/ Apoiar o registo, a documentação e o reporte das deficiências identificadas, apresentando as respectivas recomendações;<br>\n/ Acompanhar a implementação das recomendações propostas, assegurando que as acções correctivas são efectivamente executadas;<br>\n/ Contribuir para o cumprimento das políticas e procedimentos das unidades do banco;<br>\n/ Apoiar a emissão de pareceres e recomendações sobre projectos de normas internas ou<br>\nalterações de procedimentos;<br>\n/ Colaborar para o bom funcionamento da Direcção, de acordo com os seus conhecimentos e competências;<br>\n/ Zelar pela conservação e utilização adequada dos bens e equipamentos ao serviço do banco;<br>\n/ Executar outras tarefas no âmbito das suas funções;<br>\n/ Cumprir as orientações legais e normativos internos.</p>\n<p><strong>Habilidades e Competências</strong><br>\n/ Conhecimentos de auditoria e investigação;<br>\n/ Experiência em auditoria financeira e operacional;<br>\n/ Conhecimento das operações bancárias;<br>\n/ Elevada capacidade analítica;<br>\n/ Conhecimentos de análise financeira;<br>\n/ Conhecimento de avaliação de risco;<br>\n/ Conhecimentos regulamentares aplicáveis ao sector.</p>\n<p><strong>Data de Envio de Candidaturas</strong><br>\nOs(as) candidatos(as) interessados(as) deverão submeter a sua candidatura até 08 de Maio de 2026, mencionando a referência <strong>Invest_2026</strong>, para o endereço de correio electrónico.</p>\n<h3><strong>📩 COMO CANDIDATAR-SE</strong></h3>\n<p></p>Passos para se inscrever:<p>Faça a sua candidatura através do e-mail: http://recrutamento@accessbankplc.com</p>\n            Partilhar:\n            <i></i>\n            <i></i>\n            <i></i>\n                Categorias\n                                      Admininistração e Gestão\n                                      Administrativo e Secretariado\n                                      Agropecuária e Pesca\n                                      Alimentação e Nutrição\n                                      Ambiente\n                                      Arquitectura\n                                      Atendimento ao Cliente\n                                      Auditoria\n                                      Aviação\n                                      Banca e Seguros\n                                      Beleza\n                                      Bolsas de Estudos\n                                      Comercial\n                                      Comunicação Social\n                                      Concurso Público\n                                      Construção Civil\n                                      Consultoria\n                                      Contabilidade\n                                      Costura\n                                      Cozinha\n                                      Culinária\n                                      Design\n                                      Desportos\n                                      Economia\n                                      Educação e Ensino\n                                      Electricidade\n                                      Engenharia\n                                      Estágio\n                                      Estética\n                                      Farmácia\n                                      Finanças\n                                      Fotografia e Vídeo\n                                      Freelancer\n                                      Hotelaria e Turismo\n                                      Informática e Tecnologias\n                                      Jurídico\n                                      Línguas\n                                      Logística\n                                      Marketing Digital\n                                      Marketing e Publicidade\n                                      Mecánica\n                                      Medicina\n                                      Petrolífero\n                                      Recursos Humanos\n                                      Transportes\n                Vagas Recentes\n                    <i></i>\n                      Vaga para Comercial — Frutas &amp; Legumes\n                      Agrogenea Distribuição\n                    <i></i>\n                      Vaga para Chefe de Secção de Brand &amp; Communications (Benguela)\n                      Africell Angola\n                    <i></i>\n                      Vaga para Coordenador de Oficina Mecânica\n                      Saipem\n                    <i></i>\n                      Vaga para Técnico de Trade Finance\n                      Standard Bank Angola\n                    <i></i>\n                      Vaga para Senior Accountant (Contabilista Sénior)\n                      St. George\n                    <i></i>\n                      Vaga para QHSE Manager (Gestor de Qualidade, Saúde, Segurança e Ambiente)\n                      ES&amp;S Group (Exceptional Service &amp; Supply)\n                    <i></i>\n                      Vaga para Recepcionista\n                      CNCEC International (Sucursal Angola)\n                    <i></i>\n                      Vaga para Assistente Comercial\n                      Access Bank Angola","excerpt":"Sobre a vaga Os(as) candidatos(as) interessados(as) deverão submeter a sua candidatura até 08 de Maio de 2026, mencionando a referência Invest_2026 , para o endereço de correio electrónico. Estamos a recrutar Técnico(a) de Investigação de Auditoria Formação / Licenciatura em Economia, Auditoria, Ges","apply_url":"http://recrutamento@accessbankplc.com","salary":"","posted_at":"2026-05-05T07:30:26.000Z","id":"vaga-para-tecnicoa-de-investigacao-de-auditoria","first_seen_at":"2026-07-18T16:39:17.270Z","score":40,"logo_url":"https://logo.pubrio.com/accessbankplc.com","description_enriched":"<h3><strong>Sobre a vaga</strong></h3>\n<p>Os(as) candidatos(as) interessados(as) deverão submeter a sua candidatura até 08 de Maio de 2026, mencionando a referência <strong>Invest_2026</strong>, para o endereço de correio electrónico.</p>\n<p>Estamos a recrutar</p>\n<p><strong>Técnico(a) de Investigação de Auditoria</strong></p>\n<p><strong>Formação</strong><br>\n/ Licenciatura em Economia, Auditoria, Gestão de Empresas, Finanças, Contabilidade ou área<br>\nsimilar.</p>\n<p><strong>Experiência</strong><br>\n/ Experiência mínima de 2 anos em funções relacionadas com auditoria (interna e externa), compliance e controlo interno, preferencialmente no setor bancário.</p>\n<p><strong>Principais Responsabilidades</strong><br>\n/ Efectuar auditorias aos departamentos, cumprindo rigorosamente o calendário definido;<br>\n/ Recolher e analisar a informação disponibilizada;<br>\n/ Elaborar relatórios e propor recomendações com vista à melhoria da eficácia dos serviços;<br>\n/ Produzir relatórios sobre o controlo interno dos processos existentes nos diferentes departamentos;<br>\n/ Acompanhar e prestar apoio ao auditor externo, sempre que necessário;<br>\n/ Reportar regularmente informações relevantes que possam ter impacto nas actividades da instituição;<br>\n/ Apoiar o registo, a documentação e o reporte das deficiências identificadas, apresentando as respectivas recomendações;<br>\n/ Acompanhar a implementação das recomendações propostas, assegurando que as acções correctivas são efectivamente executadas;<br>\n/ Contribuir para o cumprimento das políticas e procedimentos das unidades do banco;<br>\n/ Apoiar a emissão de pareceres e recomendações sobre projectos de normas internas ou<br>\nalterações de procedimentos;<br>\n/ Colaborar para o bom funcionamento da Direcção, de acordo com os seus conhecimentos e competências;<br>\n/ Zelar pela conservação e utilização adequada dos bens e equipamentos ao serviço do banco;<br>\n/ Executar outras tarefas no âmbito das suas funções;<br>\n/ Cumprir as orientações legais e normativos internos.</p>\n<p><strong>Habilidades e Competências</strong><br>\n/ Conhecimentos de auditoria e investigação;<br>\n/ Experiência em auditoria financeira e operacional;<br>\n/ Conhecimento das operações bancárias;<br>\n/ Elevada capacidade analítica;<br>\n/ Conhecimentos de análise financeira;<br>\n/ Conhecimento de avaliação de risco;<br>\n/ Conhecimentos regulamentares aplicáveis ao sector.</p>\n<p><strong>Data de Envio de Candidaturas</strong><br>\nOs(as) candidatos(as) interessados(as) deverão submeter a sua candidatura até 08 de Maio de 2026, mencionando a referência <strong>Invest_2026</strong>, para o endereço de correio electrónico.</p>\n<h3><strong>📩 COMO CANDIDATAR-SE</strong></h3>\n<p></p>Passos para se inscrever:<p>Faça a sua candidatura através do e-mail: http://recrutamento@accessbankplc.com</p>\n            Partilhar:\n            <i></i>\n            <i></i>\n            <i></i>\n                Categorias\n                                      Admininistração e Gestão\n                                      Administrativo e Secretariado\n                                      Agropecuária e Pesca\n                                      Alimentação e Nutrição\n                                      Ambiente\n                                      Arquitectura\n                                      Atendimento ao Cliente\n                                      Auditoria\n                                      Aviação\n                                      Banca e Seguros\n                                      Beleza\n                                      Bolsas de Estudos\n                                      Comercial\n                                      Comunicação Social\n                                      Concurso Público\n                                      Construção Civil\n                                      Consultoria\n                                      Contabilidade\n                                      Costura\n                                      Cozinha\n                                      Culinária\n                                      Design\n                                      Desportos\n                                      Economia\n                                      Educação e Ensino\n                                      Electricidade\n                                      Engenharia\n                                      Estágio\n                                      Estética\n                                      Farmácia\n                                      Finanças\n                                      Fotografia e Vídeo\n                                      Freelancer\n                                      Hotelaria e Turismo\n                                      Informática e Tecnologias\n                                      Jurídico\n                                      Línguas\n                                      Logística\n                                      Marketing Digital\n                                      Marketing e Publicidade\n                                      Mecánica\n                                      Medicina\n                                      Petrolífero\n                                      Recursos Humanos\n                                      Transportes\n                Vagas Recentes\n                    <i></i>\n                      Oportunidade para Técnico de Trade Finance\n                      Standard Bank Angola\n                    <i></i>\n                      Grande Oportunidade: Recrutamento de Empregado(a) Doméstico(a) Temporário(a) na Embaixada do Japão em Angola\n                      Embaixada do Japão na República de Angola\n                    <i></i>\n                      Vaga: Chefe de Campo (Camp Boss) em Angola - NEWREST Restauração\n                      NEWREST Restauração, Lda\n                    <i></i>\n                      Vaga para Gestor de QHSE\n                      ES&amp;S Group\n                    <i></i>\n                      Grande Oportunidade para Senior Accountant\n                      St. George\n                    <i></i>\n                      Oportunidade Urgente: Comercial para Frutas &amp; Legumes\n                      Agrogenea Distribuição\n                    <i></i>\n                      Vaga para Chefe de Secção de Brand &amp; Communications em Benguela\n                      Africell Angola\n                    <i></i>\n                      Oportunidade para Coordenador de Oficina Mecânica\n                      Saipem","tipo_contrato":"","modalidade":"","requisitos":"","beneficios":""}